django_signoff/__init__.py
django_signoff/apps.py
django_signoff/middleware.py
django_signoff/models.py
django_signoff/urls.py
django_signoff/views.py
django_signoff/static/css/django_signoff.css
django_signoff/static/js/django_signoff.js
django_signoff/templates/django_signoff/base.html
django_signoff-0.1.1.dist-info/DESCRIPTION.rst
django_signoff-0.1.1.dist-info/METADATA
django_signoff-0.1.1.dist-info/RECORD
django_signoff-0.1.1.dist-info/WHEEL
django_signoff-0.1.1.dist-info/metadata.json
django_signoff-0.1.1.dist-info/top_level.txt
signoff/__init__.py
signoff/admin.py
signoff/apps.py
signoff/middleware.py
signoff/models.py
signoff/urls.py
signoff/views.py
signoff/migrations/0001_initial.py
signoff/migrations/0002_documentconsent_signed_name.py
signoff/migrations/__init__.py
signoff/static/css/django_signoff.css
signoff/static/js/django_signoff.js
signoff/templates/signoff/base.html
signoff/templates/signoff/document.html
signoff/templates/signoff/index.html
