Metadata-Version: 2.0
Name: django-signoff
Version: 0.1.1
Summary: Present users with your Terms of Service and other documents, and record their consent
Home-page: https://github.com/dcollinsn/django-signoff
Author: Dan Collins
Author-email: dan@dcollins.cc
License: MIT
Keywords: django-signoff
Platform: UNKNOWN
Classifier: Development Status :: 3 - Alpha
Classifier: Framework :: Django :: 2.0
Classifier: Intended Audience :: Developers
Classifier: License :: OSI Approved :: BSD License
Classifier: Natural Language :: English
Classifier: Programming Language :: Python :: 2
Classifier: Programming Language :: Python :: 2.7
Classifier: Programming Language :: Python :: 3
Classifier: Programming Language :: Python :: 3.4
Classifier: Programming Language :: Python :: 3.5
Classifier: Programming Language :: Python :: 3.6
Requires-Dist: django-model-utils (>=2.0)
